[
{
"id": "488943",
"type_id": "5",
"title": "\u7f51\u7ea6\u8f66\u53f8\u673a\u906d\u52ab\u53cd\u6297 3\u6839\u624b\u6307\u88ab\u5272\u65ad",
"summary": "\u539f\u6807\u9898\uff1a\u53eb\"\u6ef4\u6ef4\"\u52ab\u53f8\u673a\u8d4c\u5f92\u901e\u51f6\u65ad\u4eba\u6307\u5e7f\u5dde\u65e5\u62a5\u8baf(\u8bb0\u8005\u5d14\u5b81\u5b81\u901a\u8baf\u5458\u9ec4\u5b87\u3001\u6797\u4e00\u7a0b)\u8fd1\u5e74\u6765\uff0c\u5305\u62ec\u7f51\u7ea6\u8f66\u5728\u5185...",
"img": "",
"src_img": "",
"sitename": "\u65b0\u6d6a\u79d1\u6280",
"addtime": "1474595900",
"use_thumb": false
},
{
"id": "488919",
"type_id": "5",
"title": "\u9a6c\u5316\u817e\u66dd\u5fae\u4fe1\u5e94\u7528\u53f7\u6539\u540d\u5c0f\u7a0b\u5e8f\u5185\u5e55\uff1a\u82f9\u679c\u4e0d\u5141\u8bb8",
"summary": "\u3010TechWeb\u62a5\u9053\u30119\u670823\u65e5\u6d88\u606f\uff0c\u5fae\u535a\u5b9e\u540d\u8ba4\u8bc1\u7528\u6237\u66dd\u5149\u7684\u670b\u53cb\u5708\u622a\u56fe\u663e\u793a\uff0c\u7591\u4f3c\u9a6c\u5316\u817e\u5728\u5f20\u5c0f\u9f99\u670b\u53cb\u5708\u4e0b\u7684\u7559\u8a00...",
"img": "http:\/\/news.coolban.com\/Upload\/thumb\/160923\/80-60-0Z0033I4-0.jpg",
"src_img": "http:\/\/upload.techweb.com.cn\/2016\/0923\/1474591237800.jpg",
"sitename": "techweb",
"addtime": "1474592482",
"use_thumb": false
},
{
"id": "488888",
"type_id": "5",
"title": "\u65af\u8482\u82ac\u00b7\u970d\u91d1\u548c\u5176\u4ed6374\u4f4d\u79d1\u5b66\u5bb6\u547c\u5401\u4e0d\u8981\u6295\u7968\u652f\u6301\u7279\u6717\u666e",
"summary": "\u79d1\u5b66\u5bb6\u8868\u793a\uff1a\u201c\u5171\u548c\u515a\u603b\u7edf\u5019\u9009\u4eba\u4e3b\u5f20\u7f8e\u56fd\u9000\u51fa\u300a\u5df4\u9ece\u534f\u5b9a\u300b\u7684\u8a00\u8bba\u9700\u8981\u5f15\u8d77\u9ad8\u5ea6\u91cd\u89c6\u3002\u300a\u5df4\u9ece\u534f\u5b9a\u300b\u662f\u5168\u740319...",
"img": "http:\/\/news.coolban.com\/Upload\/thumb\/160923\/80-60-0RF51919-0.jpg",
"src_img": "http:\/\/static.cnbetacdn.com\/thumb\/article\/2016\/0922\/9f4e884ca9c285f.jpg_600x600.jpg",
"sitename": "cnBeta",
"addtime": "1474590869",
"use_thumb": false
},
{
"id": "488883",
"type_id": "4",
"title": "\u8fdb\u53ef\u653b\u9000\u53ef\u5b88\uff0c\u5f00\u653e\u79c1\u5bb6\u8f66\u7684\u795e\u5dde\u8ba9\u6ef4\u6ef4\u5de6\u53f3\u4e3a\u96be",
"summary": "9\u670822\u65e5\uff0c\u795e\u5dde\u4e13\u8f66\u6b63\u5f0f\u5411\u5916\u53d1\u5e03U+\u5f00\u653e\u5e73\u53f0\u6218\u7565\uff0c\u5ba3\u5e03\u5411\u7b26\u5408\u6761\u4ef6\u7684\u5168\u56fd\u8f66\u4e3b\u514d\u8d39\u5f00\u653e\u6d41\u91cf\u3001\u6280\u672f\u548c\u54c1\u724c\u8d44\u6e90...",
"img": "http:\/\/news.coolban.com\/Upload\/thumb\/160923\/80-60-0RFGM2-0.jpg",
"src_img": "http:\/\/7xil86.com2.z0.glb.qiniucdn.com\/uploads\/images\/2016\/09\/177.jpeg",
"sitename": "\u949b\u5a92\u4f53",
"addtime": "1474590614",
"use_thumb": false
},
{
"id": "488877",
"type_id": "5",
"title": "\u4e09\u661f\uff1a\u6536\u523026\u8d77\u865a\u5047Galaxy Note 7\u7206\u70b8\u62a5\u544a",
"summary": "\u4e09\u661f\u5728\u540e\u7eed\u8c03\u67e5\u4e2d\u53d1\u73b0\uff0c\u5176\u4e2d12\u8d77\u62a5\u544a\u4e2d\u53d1\u73b0\u548cNote7\u6ca1\u6709\u4efb\u4f55\u5173\u7cfb\uff1b\u57287\u8d77\u62a5\u544a\u4e2d\uff0c\u4e09\u661f\u5b98\u65b9\u65e0\u6cd5\u8054\u7cfb\u5230\u62b1\u6028\u7684...",
"img": "http:\/\/news.coolban.com\/Upload\/thumb\/160923\/80-60-0RF4G05-0.jpg",
"src_img": "http:\/\/static.cnbetacdn.com\/thumb\/article\/2016\/0922\/f359dd08c355e70.jpg_600x600.jpg",
"sitename": "cnBeta",
"addtime": "1474590508",
"use_thumb": false
},
{
"id": "488863",
"type_id": "5",
"title": "\u66b4\u9f99\u773c\u955c\u751f\u4ea7\u5546\u8d77\u8bc9\u963f\u91cc\u5df4\u5df4\u8981\u6c42\u62ab\u9732\u552e\u5047\u8005\u4fe1\u606f",
"summary": "\u3010TechWeb\u62a5\u9053\u30119\u670823\u65e5\u6d88\u606f\uff0c\u56e0\u65e0\u6cd5\u83b7\u5f97\u552e\u5047\u8005\u4fe1\u606f\uff0c“BOLON\u66b4\u9f99”\u5546\u6807\u6301\u6709\u8005\u3001\u66b4\u9f99\u773c\u955c\u751f\u4ea7...",
"img": "http:\/\/news.coolban.com\/Upload\/thumb\/160923\/80-60-0P0043417-0.jpg",
"src_img": "http:\/\/upload.techweb.com.cn\/2016\/0923\/1474587091490.jpg",
"sitename": "techweb",
"addtime": "1474589273",
"use_thumb": false
},
{
"id": "488853",
"type_id": "4",
"title": "\u5929\u5929\u52a8\u542c\u5173\u505c\uff0c\u867e\u7c73\u97f3\u4e50\u4f1a\u6301\u7eed\u9668\u843d\u8fd8\u662f\u4e0a\u6f14\u53cd\u8f6c\uff1f",
"summary": "\u5929\u5929\u52a8\u542c\u8981\u505c\u6b62\u670d\u52a1\u4e86\uff0c\u542c\u5230\u8fd9\u4e2a\u6d88\u606f\u5b8c\u5168\u4e0d\u60ca\u8bb6\uff0c\u53cd\u5012\u662f\u7f51\u53cb\u5bf9\u8fd9\u4e00\u6d88\u606f\u7684\u53cd\u5e94\uff0c\u624d\u66f4\u8ba9\u4eba\u611f\u53f9\u539f\u6765\u5927\u4f17\u5bf9\u4ea7...",
"img": "http:\/\/news.coolban.com\/Upload\/thumb\/160923\/80-60-0HFB509-0.jpg",
"src_img": "http:\/\/f.hiphotos.baidu.com\/news\/w%3D638\/sign=1b829f5ac61b9d168ac79962cbdfb4eb\/6d81800a19d8bc3edc710b4f8a8ba61ea8d3453d.jpg",
"sitename": "\u767e\u5bb6\u81ea\u5a92\u4f53",
"addtime": "1474587067",
"use_thumb": false
},
{
"id": "488851",
"type_id": "4",
"title": "\u8d85\u8fc71\u4ebf\u4eba\u4e3a\u97f3\u4e50\u6d41\u5a92\u4f53\u4ed8\u8d39\uff0c5\u4ebf\u4eba\u4e5f\u4e0d\u4f1a\u592a\u8fdc\u4e86\uff01",
"summary": "\u7f16\u8bd1\u4e28\u8bb8\u6893\u70c1\u597d\u6d88\u606f\u6765\u4e86\uff01\u672c\u6708\uff0c\u6d41\u5a92\u4f53\u97f3\u4e50\u670d\u52a1\u4ed8\u8d39\u7528\u6237\u6210\u529f\u8de8\u8fc71\u4ebf\u5927\u5173\uff0cSpotify\uff0cSiriusXMRadio\u548cApple...",
"img": "http:\/\/news.coolban.com\/Upload\/thumb\/160923\/80-60-0HF33H7-0.jpg",
"src_img": "http:\/\/g.hiphotos.baidu.com\/news\/w%3D638\/sign=98e852d6fe246b607b0eb177d3fa1a35\/b3119313b07eca8043d93562992397dda0448352.jpg",
"sitename": "\u767e\u5bb6\u81ea\u5a92\u4f53",
"addtime": "1474586860",
"use_thumb": false
},
{
"id": "488831",
"type_id": "4",
"title": "\u4e8c\u5408\u4e00\u6210PC\u5fc5\u4e89\u4e4b\u5730\uff0cYOGA BOOK\u80fd\u5426\u52a9\u8054\u60f3\u66f4\u8fdb\u4e00\u6b65",
"summary": "\u4f5c\u8005\uff1a\u9f9a\u8fdb\u8f89\u6628\u665a\uff0c\u6700\u5177\u4efd\u91cf\u7684\u56fd\u9645PC\u5382\u5546\u8054\u60f3\u5728\u903c\u683c\u95ea\u95ea\u7684\u51e4\u51f0\u56fd\u9645\u4f20\u5a92\u4e2d\u5fc3\u53d1\u5e03\u9177\u70ab\u65e0\u6bd4\u7684\u4e8c\u5408\u4e00\u5e73\u677f\u7535\u8111...",
"img": "http:\/\/news.coolban.com\/Upload\/thumb\/160923\/80-60-052QW227-0.jpg",
"src_img": "http:\/\/a.hiphotos.baidu.com\/news\/w%3D638\/sign=c2ac413cdc3f8794d3ff4b2dea190ead\/ac4bd11373f082020a4633bb43fbfbedaa641b59.jpg",
"sitename": "\u767e\u5bb6\u81ea\u5a92\u4f53",
"addtime": "1474585185",
"use_thumb": false
},
{
"id": "488828",
"type_id": "4",
"title": "BOSS\u76f4\u8058\uff1a\u5e72\u6389\u4e2d\u4ecb\u7684\u751f\u610f\u6b23\u6b23\u5411\u8363",
"summary": "\u6587|\u9611\u5915BOSS\u76f4\u8058\u8fde\u7eed\u5b8c\u6210C1\u3001C2\u8f6e\u878d\u8d44\uff0c\u4f5c\u4e3a\u4e00\u5bb6\u6210\u7acb\u4e0d\u5230\u4e09\u5e74\u7684\u521b\u4e1a\u516c\u53f8\uff0c\u5728\u8fd9\u79cd\u5929\u6c14\u4e0b\uff0c\u8fd9\u79cd\u878d\u8d44\u9891\u7387\u76f8...",
"img": "http:\/\/news.coolban.com\/Upload\/thumb\/160923\/80-60-052Q44643-0.jpg",
"src_img": "http:\/\/b.hiphotos.baidu.com\/news\/w%3D638\/sign=0cfe3d7ed9c8a786be2a490d5f0bc9c7\/ac6eddc451da81cb103a1e495a66d01608243151.jpg",
"sitename": "\u767e\u5bb6\u81ea\u5a92\u4f53",
"addtime": "1474584669",
"use_thumb": false
},
{
"id": "488826",
"type_id": "4",
"title": "\u8fd9\u4e9b\u5e74\uff0c\u62cd\u7247\u7684\u548c\u770b\u7247\u7684",
"summary": "\u6587|\u9611\u5915\u6700\u8fd1\u8fd9\u4e9b\u65f6\u65e5\uff0c\u706b\u8d77\u6765\u7684\u5e7f\u544a\u7247\u633a\u591a\u3002\u7d22\u5c3cPS4\u964d\u4ef7\u7684\u5e7f\u544a\u7247\uff0c\u9b54\u6027\u6d17\u8111\uff0c\u4e00\u8d2f\u7684\u7d22\u5c3c\u5927\u6cd5\u597d\u610f\u5473\u3002\u73e0\u6d77...",
"img": "http:\/\/news.coolban.com\/Upload\/thumb\/160923\/80-60-052Q21350-0.jpg",
"src_img": "http:\/\/e.hiphotos.baidu.com\/news\/w%3D638\/sign=cad60e7874d98d1076d40f32193eb807\/3b292df5e0fe9925583af1d43ca85edf8db17104.jpg",
"sitename": "\u767e\u5bb6\u81ea\u5a92\u4f53",
"addtime": "1474584459",
"use_thumb": false
},
{
"id": "488824",
"type_id": "4",
"title": "\u9a6c\u5316\u817e12\u5e74\u524d\u89c6\u9891\u6252\u51fa\uff01\u5411\u6d77\u5c14\u603b\u88c1\u5f20\u745e\u654f\u63a8\u9500QQ\u88ab\u62d2",
"summary": "2004\u5e7412\u6708\uff0c\u4e2d\u592e\u7535\u89c6\u53f0\u201c\u5e74\u5ea6\u5341\u5927\u7ecf\u6d4e\u4eba\u7269\u201d\u63ed\u699c\uff0c\u9a6c\u5316\u817e\u4f5c\u4e3a\u5019\u9009\u4e4b\u4e00\u5e76\u672a\u83b7\u8bc4\uff0c\u53ea\u662f\u62ff\u5230\u4e86\u65b0\u9510\u4eba\u7269\u5956\u3002...",
"img": "http:\/\/news.coolban.com\/Upload\/thumb\/160923\/80-60-052Q0G15-0.jpg",
"src_img": "http:\/\/b.hiphotos.baidu.com\/news\/w%3D638\/sign=12c7119063600c33f079ddcb224d5134\/9213b07eca806538757376979fdda144ac34829d.jpg",
"sitename": "\u767e\u5bb6\u81ea\u5a92\u4f53",
"addtime": "1474584189",
"use_thumb": false
},
{
"id": "488821",
"type_id": "4",
"title": "\u674e\u6210\u4e1c\uff1a\u4e3a\u4ec0\u4e48\u300cC2B\u5b9a\u5236\u300d\u4f1a\u98a0\u8986\u4f20\u7edf\u670d\u88c5\u7535\u5546\uff1f",
"summary": "\u4f26\u6566\u65f6\u95f49\u670819\u65e5\uff0c\u4eac\u4e1c\u548cEVEdeCINA\u3001NE\u00b7TIGER\u3001KevinKelly\u3001ByCreations\u00b7\u67cf\u54c1\u3001X\u00b7Lando\u3001\u6052\u7f8e\u745e\u73e0\u5b9d\u516d...",
"img": "http:\/\/news.coolban.com\/Upload\/thumb\/160922\/80-60-232P23539-0.jpg",
"src_img": "http:\/\/g.hiphotos.baidu.com\/news\/w%3D638\/sign=1d8b0a01c1ea15ce41eee30a8e013a25\/77094b36acaf2eddbd7c2d6d851001e9380193a0.jpg",
"sitename": "\u767e\u5bb6\u81ea\u5a92\u4f53",
"addtime": "1474583989",
"use_thumb": false
},
{
"id": "488809",
"type_id": "4",
"title": "\u9ed1\u9a6c\u4e50\u89c6\u79fb\u52a8\u4e00\u9ed1\u5230\u5e95 \u56e0\u6293\u4f4f\u4e86\u8fd9\u4e00\u56fd\u6c11\u6027\u75db\u70b9\uff01",
"summary": "\u6587\/\u6613\u5317\u8fb0\u91d1\u4e5d\u94f6\u5341\uff0c\u623f\u5730\u4ea7\u5708\u5982\u6b64\u3002\u5bf9\u4e8e\u79d1\u6280\u5708\uff0c\u4ea6\u7136\u30029\u6708\u7684\u5317\u4eac\u662f\u91d1\u8272\uff0c\u8def\u65c1\u7684\u94f6\u674f\u53d8\u5f97\u91d1\u707f\uff0c\u5bf9\u4e8e\u54c1\u724c\u548c...",
"img": "http:\/\/news.coolban.com\/Upload\/thumb\/160922\/80-60-232Ja217-0.jpg",
"src_img": "http:\/\/d.hiphotos.baidu.com\/news\/crop%3D0%2C26%2C550%2C330%3Bw%3D638\/sign=648dcaa6c0fcc3cea08f9373af75faba\/5d6034a85edf8db1e88e3ae00123dd54574e7495.jpg",
"sitename": "\u767e\u5bb6\u81ea\u5a92\u4f53",
"addtime": "1474583235",
"use_thumb": false
},
{
"id": "488747",
"type_id": "4",
"title": "300\u5143\u8d77\u6295\u7684\u670b\u53cb\u5708\u672c\u5730\u5e7f\u544a\uff0c\u95e8\u69db\u6ca1\u4f60\u60f3\u7684\u90a3\u4e48\u4f4e",
"summary": "\u6628\u665a\uff0c\u5fae\u4fe1\u5e7f\u544a\u7684\u5b98\u65b9\u8d26\u53f7\u201c\u5fae\u4fe1\u5e7f\u544a\u52a9\u624b\u201d\u63a8\u9001\u516c\u544a\u300a\u670b\u53cb\u5708\u672c\u5730\u63a8\u5e7f\u5e7f\u544a\u6b63\u5f0f\u4e0a\u7ebf\u300b\uff0c\u6b63\u6587\u5f00\u7bc7\u4fbf\u63d0\u5230\uff1a\u4eca...",
"img": "http:\/\/news.coolban.com\/Upload\/thumb\/160922\/80-60-2100492036-0.jpg",
"src_img": "http:\/\/f.hiphotos.baidu.com\/news\/w%3D638\/sign=5c147224fe03738dde4a0f218b1ab073\/03087bf40ad162d917c66f9819dfa9ec8a13cd0e.jpg",
"sitename": "\u767e\u5bb6\u81ea\u5a92\u4f53",
"addtime": "1474551470",
"use_thumb": false
},
{
"id": "488744",
"type_id": "4",
"title": "\u60f3\u77e5\u9053\u7845\u8c37\u7684\u79d8\u5bc6\uff1f\u5c31\u85cf\u5728\u4ed6\u7684\u4e66\u623f\u91cc",
"summary": "\u6211\u7b2c\u4e00\u6b21\u8d70\u8fdb\u5b89\u5fb7\u68ee-\u970d\u6d1b\u7ef4\u8328\u57fa\u91d1\uff08AndreessenHorowitz\uff09\u7684\u5927\u5385\u65f6\uff0c\u6709\u56db\u4e2a\u4eba\u6b63\u5728\u9760\u5899\u7684\u5730\u65b9\u7b49\u5019\u3002\u5176\u4e2d\u4e24...",
"img": "http:\/\/news.coolban.com\/Upload\/thumb\/160922\/80-60-21004A017-0.jpg",
"src_img": "http:\/\/c.hiphotos.baidu.com\/news\/crop%3D0%2C57%2C1024%2C614%3Bw%3D638\/sign=1bca802da1014c080d7472e5374b2e3d\/a1ec08fa513d2697ab0005d95dfbb2fb4216d867.jpg",
"sitename": "\u767e\u5bb6\u81ea\u5a92\u4f53",
"addtime": "1474551196",
"use_thumb": false
},
{
"id": "488690",
"type_id": "4",
"title": "\u6d77\u5c14\u53d1\u660e\u65e0\u538b\u7f29\u673a\u8584\u819c\u56fa\u6001\u5236\u51b7\u5176\u610f\u4e49\u4e0d\u4e9a\u4e8eiPhone",
"summary": "\u79f0\u5236\u51b7\u6280\u672f\u4e3a\u5bb6\u7535\u4ea7\u54c1\u7684\u6838\u5fc3\u6280\u672f\u6beb\u4e0d\u4e3a\u8fc7\uff0c\u5728\u7a7a\u8c03\u548c\u4ee5\u51b0\u7bb1\u4e3a\u4e3b\u7684\u98df\u54c1\u50a8\u85cf\u8bbe\u5907\u4e2d\uff0c\u505a\u597d\u5236\u51b7\u5de5\u4f5c\uff0c\u624d\u662f\u5b9e\u73b0...",
"img": "http:\/\/news.coolban.com\/Upload\/thumb\/160922\/80-60-1Z0415640-0.jpg",
"src_img": "http:\/\/d.hiphotos.baidu.com\/news\/w%3D638\/sign=60174396474a20a4311e3fc4a8539847\/5ab5c9ea15ce36d3f63898b432f33a87e950b171.jpg",
"sitename": "\u767e\u5bb6\u81ea\u5a92\u4f53",
"addtime": "1474543567",
"use_thumb": false
},
{
"id": "488645",
"type_id": "4",
"title": "\u79bb\u804c\u4e00\u5e74\u540e\u7adf\u7136\u88ab\u5f00\u9664\uff0c\u767e\u5ea6\u5458\u5de5\u4e0e\u804c\u4e1a\u9053\u5fb7\u59d4\u5458\u4f1a\u6253\u8d77\u4e86\u53e3\u6c34\u4ed7",
"summary": "\u7531\u4e8e\u591a\u6b21\u5f00\u51fa\u4e25\u91cd\u8fdd\u7eaa\u901a\u62a5\u4fe1\uff0c\u767e\u5ea6\u516c\u53f8\u804c\u4e1a\u9053\u5fb7\u59d4\u5458\u4f1a\u5728\u4eca\u5e74\u9887\u53d7\u5173\u6ce8\u3002\u5c31\u5728\u8fd1\u65e5\uff0c\u8fd9\u4e2a\u795e\u79d8\u7684\u767e\u5ea6\u5185\u90e8\u673a\u6784...",
"img": "http:\/\/news.coolban.com\/Upload\/thumb\/160922\/80-60-1HF64456-0.jpg",
"src_img": "http:\/\/7xil86.com2.z0.glb.qiniucdn.com\/uploads\/images\/2016\/09\/4509031211395678.jpg",
"sitename": "\u949b\u5a92\u4f53",
"addtime": "1474536856",
"use_thumb": false
},
{
"id": "488627",
"type_id": "4",
"title": "\u4e3a\u4ec0\u4e48\u4e50\u89c6\u660e\u660e\u8bf4\u8981\u9020\u8f66 \u5374\u9020\u51fa\u4e2a\u6253\u8f66\u8f6f\u4ef6\uff1f",
"summary": "\u8fd8\u8bb0\u5f97\u4e24\u5e74\u524d\u7684\u90a3\u4e2a\u96fe\u973e\u6df1\u91cd\u7684\u51ac\u5929\uff0c\u4e50\u89c6\u6b63\u5f0f\u5ba3\u5e03\u8981\u8fdb\u5165\u7535\u52a8\u6c7d\u8f66\u5e02\u573a\u7684\u201cSEE\u8ba1\u5212\u201d\u8ba9\u4eba\u8bb0\u5fc6\u72b9\u65b0\u3002\u63a5\u4e0b\u6765...",
"img": "http:\/\/news.coolban.com\/Upload\/thumb\/160922\/80-60-162S4OV-0.jpg",
"src_img": "http:\/\/a.hiphotos.baidu.com\/news\/w%3D638\/sign=8740a41a8a26cffc692abcb181004a7d\/b999a9014c086e062d90edc80a087bf40ad1cb7d.jpg",
"sitename": "\u767e\u5bb6\u81ea\u5a92\u4f53",
"addtime": "1474535672",
"use_thumb": false
},
{
"id": "488622",
"type_id": "5",
"title": "\u65b0\u534e\u793e\uff1a\u4e0b\u597d\u5171\u4eab\u5927\u68cb\uff0c\u65e0\u8f66\u53ef\u80dc\u6709\u8f66",
"summary": "\u65b0\u534e\u793e\u5317\u4eac9\u670822\u65e5\u7535\u9898\uff1a\u4e0b\u597d\u5171\u4eab\u5927\u68cb\uff0c\u65e0\u8f66\u53ef\u80dc\u6709\u8f669\u670822\u65e5\uff0c\u662f\u4e16\u754c\u65e0\u8f66\u65e5\u3002\u968f\u7740\u6c7d\u8f66\u7684\u666e\u53ca\uff0c\"\u5f00\u8f66\u5835\u3001...",
"img": "",
"src_img": "",
"sitename": "\u65b0\u6d6a\u79d1\u6280",
"addtime": "1474535416",
"use_thumb": false
}
]